pyPreservicaGov/__init__.py
pyPreservicaGov/__main__.py
pyPreservicaGov/main.py
pyPreservicaGov/schema.py
pyPreservicaGov/images/committee.png
pyPreservicaGov/images/meeting.png
pyPreservicaGov/schema/mg-attachment-CMIS.xsl
pyPreservicaGov/schema/mg-attachment-Index.xml
pyPreservicaGov/schema/mg-attachment-schema.xsd
pyPreservicaGov/schema/mg-committee-CMIS.xsl
pyPreservicaGov/schema/mg-committee-Index.xml
pyPreservicaGov/schema/mg-committee-schema.xsd
pyPreservicaGov/schema/mg-meeting-CMIS.xsl
pyPreservicaGov/schema/mg-meeting-Index.xml
pyPreservicaGov/schema/mg-meeting-schema.xsd
pypreservicagov-1.0.1.dist-info/licenses/LICENSE
pypreservicagov-1.0.1.dist-info/METADATA
pypreservicagov-1.0.1.dist-info/WHEEL
pypreservicagov-1.0.1.dist-info/top_level.txt
pypreservicagov-1.0.1.dist-info/RECORD
