Metadata-Version: 2.4
Name: pyPreservicaGov
Version: 1.0.1
Summary: Python Library For Harvesting Modern.Gov Records into Preservica for Long Term Preservation
Home-page: https://pypreservicagov.readthedocs.io/
Author: James Carr
Author-email: drjamescarr@gmail.com
License: Apache License 2.0
Project-URL: Documentation, https://pypreservicagov.readthedocs.io/
Project-URL: Source, https://github.com/carj/pyPreservica.Gov
Project-URL: Discussion Forum, https://groups.google.com/g/pyPreservicaGov
Keywords: Preservica API Preservation Modern.Gov Civica
Classifier: Programming Language :: Python :: 3
Classifier: Programming Language :: Python :: 3.7
Classifier: Programming Language :: Python :: 3.8
Classifier: Programming Language :: Python :: 3.9
Classifier: Programming Language :: Python :: 3.10
Classifier: License :: OSI Approved :: Apache Software License
Classifier: Operating System :: OS Independent
Classifier: Topic :: System :: Archiving
License-File: LICENSE
Requires-Dist: pyPreservica
Requires-Dist: python-dateutil
Requires-Dist: bs4
Requires-Dist: pathvalidate
Requires-Dist: readchar
Dynamic: author
Dynamic: author-email
Dynamic: classifier
Dynamic: description
Dynamic: description-content-type
Dynamic: home-page
Dynamic: keywords
Dynamic: license
Dynamic: license-file
Dynamic: project-url
Dynamic: requires-dist
Dynamic: summary
